veeksha/__init__.py
veeksha/__main__.py
veeksha/_version.py
veeksha/benchmark.py
veeksha/benchmark_data_utils.py
veeksha/benchmark_utils.py
veeksha/capacity_search.py
veeksha/health.py
veeksha/logger.py
veeksha/sweep_summary.py
veeksha/version.py
veeksha/wandb_integration.py
veeksha/cli/__init__.py
veeksha/cli/benchmarks.py
veeksha/cli/config.py
veeksha/cli/config_docs_generator.py
veeksha/cli/config_explorer.py
veeksha/client/__init__.py
veeksha/client/base.py
veeksha/client/openai_base.py
veeksha/client/openai_chat.py
veeksha/client/openai_completions.py
veeksha/client/openai_router.py
veeksha/client/registry.py
veeksha/config/__init__.py
veeksha/config/benchmark.py
veeksha/config/capacity_search.py
veeksha/config/client.py
veeksha/config/evaluator.py
veeksha/config/runtime.py
veeksha/config/schema.py
veeksha/config/server.py
veeksha/config/slo.py
veeksha/config/trace_recorder.py
veeksha/config/traffic.py
veeksha/config/utils.py
veeksha/config/wandb.py
veeksha/config/core/__init__.py
veeksha/config/core/base_poly_config.py
veeksha/config/core/dataclass.py
veeksha/config/core/flat_dataclass.py
veeksha/config/core/frozen_dataclass.py
veeksha/config/generator/channel.py
veeksha/config/generator/interval.py
veeksha/config/generator/length.py
veeksha/config/generator/requested_output.py
veeksha/config/generator/session.py
veeksha/config/generator/session_graph.py
veeksha/core/__init__.py
veeksha/core/context.py
veeksha/core/lazy_loader.py
veeksha/core/request.py
veeksha/core/request_content.py
veeksha/core/requested_output.py
veeksha/core/response.py
veeksha/core/seeding.py
veeksha/core/session.py
veeksha/core/session_graph.py
veeksha/core/thread_pool.py
veeksha/core/tokenizer.py
veeksha/core/trace_recorder.py
veeksha/data/__init__.py
veeksha/data/corpus.txt
veeksha/evaluator/__init__.py
veeksha/evaluator/base.py
veeksha/evaluator/cdf_sketch.py
veeksha/evaluator/composite.py
veeksha/evaluator/plot_utils.py
veeksha/evaluator/registry.py
veeksha-0.2.0.dist-info/licenses/LICENSE
veeksha-0.2.0.dist-info/licenses/NOTICE.txt
veeksha-0.2.0.dist-info/METADATA
veeksha-0.2.0.dist-info/WHEEL
veeksha-0.2.0.dist-info/entry_points.txt
veeksha-0.2.0.dist-info/top_level.txt
veeksha-0.2.0.dist-info/RECORD
