Metadata-Version: 2.4
Name: veeksha
Version: 0.2.0
Summary: A framework for holistic evaluation of LLM Inference Systems
Author: Vajra Team
License: Apache-2.0
Project-URL: Homepage, https://github.com/project-vajra/veeksha
Project-URL: Documentation, https://project-vajra.github.io/veeksha
Classifier: Programming Language :: Python :: 3.12
Classifier: Programming Language :: Python :: 3.13
Classifier: Programming Language :: Python :: 3.14
Classifier: License :: OSI Approved :: Apache Software License
Classifier: Topic :: Scientific/Engineering :: Artificial Intelligence
Requires-Python: >=3.12
License-File: LICENSE
License-File: NOTICE.txt
Requires-Dist: pydantic
Requires-Dist: transformers
Requires-Dist: tqdm
Requires-Dist: ddsketch
Requires-Dist: wandb
Requires-Dist: pandas
Requires-Dist: numpy
Requires-Dist: jinja2
Requires-Dist: datasets
Requires-Dist: lm-eval
Requires-Dist: evaluate
Requires-Dist: pytablewriter
Requires-Dist: Pillow
Requires-Dist: rekha
Requires-Dist: textual
Requires-Dist: textual-plotext
Requires-Dist: requests
Requires-Dist: uvloop
Requires-Dist: httpx
Requires-Dist: nvidia-ml-py
Provides-Extra: dev
Requires-Dist: autoflake; extra == "dev"
Requires-Dist: black==25.9.0; extra == "dev"
Requires-Dist: codespell; extra == "dev"
Requires-Dist: isort==7.0.0; extra == "dev"
Requires-Dist: pyright; extra == "dev"
Requires-Dist: pytest>=8.0; extra == "dev"
Requires-Dist: pytest-cov; extra == "dev"
Requires-Dist: requests; extra == "dev"
Provides-Extra: test
Requires-Dist: pytest>=8.0; extra == "test"
Requires-Dist: pytest-cov; extra == "test"
Requires-Dist: requests; extra == "test"
Requires-Dist: vllm; extra == "test"
Requires-Dist: rich; extra == "test"
Requires-Dist: torch; extra == "test"
Requires-Dist: jinja2; extra == "test"
Dynamic: license-file
